auto_crud_param/__init__.py
auto_crud_param/crud.py
auto_crud_param/orm.py
auto_crud_param-0.2.1.dist-info/METADATA
auto_crud_param-0.2.1.dist-info/WHEEL
auto_crud_param-0.2.1.dist-info/RECORD
