Metadata-Version: 2.1
Name: auto-crud-param
Version: 0.2.1
Summary: Auto Create Retrieve Update Delete ORM Functionality for Param models using SQL alchemy.
Author: Shawn Anderson
Author-email: shawn@longtailfinancial.com
Requires-Python: >=3.10,<4.0
Classifier: Programming Language :: Python :: 3
Classifier: Programming Language :: Python :: 3.10
Classifier: Programming Language :: Python :: 3.11
Classifier: Programming Language :: Python :: 3.12
Requires-Dist: panel (>=1.3.4,<2.0.0)
Requires-Dist: param (>=2.0.1,<3.0.0)
Requires-Dist: sqlalchemy (>=2.0.23,<3.0.0)
